lanceviewer/__init__.py
lanceviewer/cli.py
lanceviewer/gcs_util.py
lanceviewer/settings.py
lanceviewer/states.py
lanceviewer/style.py
lanceviewer/table_utils.py
lanceviewer/view.py
lanceviewer-0.0.2.dist-info/METADATA
lanceviewer-0.0.2.dist-info/WHEEL
lanceviewer-0.0.2.dist-info/entry_points.txt
lanceviewer-0.0.2.dist-info/top_level.txt
lanceviewer-0.0.2.dist-info/RECORD
