Metadata-Version: 2.1
Name: lanceviewer
Version: 0.0.2
Author: dev@lance
Author-email: contact@lancedb.com
Requires-Python: >=3.8
Requires-Dist: google-cloud-storage
Requires-Dist: pylance
Requires-Dist: crcmod
Requires-Dist: duckdb
Requires-Dist: streamlit
